{ 
    "1": { 
        "id": "1", 
        "quiz_title": "JS Fundamentals", 
        "time_limit_minutes": "20", 
        "full_points": "25", 
        "author_id": "1", 
        "category_id": "2", 
        "is_visible": "0",
        "quiz_questions": [
            { 
                "id": "12", 
                "question": "Qn1 JavaScript", 
                "points": "1", 
                "type": "single choice", 
                "author_id": "1", 
                "category_id":  "2"
            },
            { 
                "id": "13", 
                "question": "Qn2 JavaScript", 
                "points": "2", 
                "type": "single choice", 
                "author_id": "1", 
                "category_id":  "2"
            },
            { 
                "id": "14", 
                "question": "Qn3 JavaScript", 
                "points": "3", 
                "type": "multiple choice", 
                "author_id": "1", 
                "category_id":  "2"
            },
            { 
                "id": "15", 
                "question": "Qn4 JavaScript", 
                "points": "4", 
                "type": "multiple choice", 
                "author_id": "1", 
                "category_id":  "2"
            },
            { 
                "id": "16", 
                "question": "Qn5 JavaScript", 
                "points": "5", 
                "type": "single choice", 
                "author_id": "1", 
                "category_id":  "2"
            }
        ]
    },
    "2": { 
        "id": "2", 
        "quiz_title": "SQL Basic", 
        "time_limit_minutes": "25", 
        "full_points": "38", 
        "author_id": "1", 
        "category_id": "1", 
        "is_visible": "0",
        "quiz_questions": []
    },
    "3": { 
        "id": "3", 
        "quiz_title": "C# Fundamentals", 
        "time_limit_minutes": "25", 
        "full_points": "66", 
        "author_id": "3", 
        "category_id": "14", 
        "is_visible": "0",
        "quiz_questions": []
    },
    "4": { 
        "id": "4", 
        "quiz_title": "SQL Qz1", 
        "time_limit_minutes": "30", 
        "full_points": "52", 
        "author_id": "26", 
        "category_id": "1", 
        "is_visible": "1",
        "quiz_questions": []
    },
    "5": { 
        "id": "5", 
        "quiz_title": "SQL Qz2", 
        "time_limit_minutes": "38", 
        "full_points": "92", 
        "author_id": "26", 
        "category_id": "1", 
        "is_visible": "1",
        "quiz_questions": []
    },
    "6": { 
        "id": "6", 
        "quiz_title": "SQL Qz3", 
        "time_limit_minutes": "25", 
        "full_points": "54", 
        "author_id": "26", 
        "category_id": "1", 
        "is_visible": "1",
        "quiz_questions": []
    },
    "7": { 
        "id": "7", 
        "quiz_title": "JavaScript Qz1", 
        "time_limit_minutes": "25", 
        "full_points": "57", 
        "author_id": "1", 
        "category_id": "2", 
        "is_visible": "1",
        "quiz_questions": [
            { 
                "id": "12", 
                "question": "Qn1 JavaScript", 
                "points": "1", 
                "type": "single choice", 
                "author_id": "1", 
                "category_id":  "2"
            },
            { 
                "id": "14", 
                "question": "Qn3 JavaScript", 
                "points": "3", 
                "type": "multiple choice", 
                "author_id": "1", 
                "category_id":  "2"
            },
            { 
                "id": "16", 
                "question": "Qn5 JavaScript", 
                "points": "5", 
                "type": "single choice", 
                "author_id": "1", 
                "category_id":  "2"
            },
            { 
                "id": "17", 
                "question": "Qn6 JavaScript", 
                "points": "6", 
                "type": "multiple choice", 
                "author_id": "1", 
                "category_id":  "2"
            },
            { 
                "id": "18", 
                "question": "Qn7 JavaScript", 
                "points": "1", 
                "type": "single choice", 
                "author_id": "1", 
                "category_id":  "2"
            },
            { 
                "id": "19", 
                "question": "Qn8 JavaScript", 
                "points": "2", 
                "type": "single choice", 
                "author_id": "1", 
                "category_id":  "2"
            }
        ]
    },
    "8": { 
        "id": "8", 
        "quiz_title": "JavaScript Qz2", 
        "time_limit_minutes": "20", 
        "full_points": "80", 
        "author_id": "48", 
        "category_id": "2", 
        "is_visible": "1",
        "quiz_questions": []
    },
    "9": { 
        "id": "9", 
        "quiz_title": "JavaScript Qz3", 
        "time_limit_minutes": "25", 
        "full_points": "84", 
        "author_id": "48", 
        "category_id": "2", 
        "is_visible": "1",
        "quiz_questions": []
    },
    "10": { 
        "id": "10", 
        "quiz_title": "Java QZ1", 
        "time_limit_minutes": "20", 
        "full_points": "58", 
        "author_id": "1", 
        "category_id": "3", 
        "is_visible": "1",
        "quiz_questions": []
    },
    "11": { 
        "id": "11", 
        "quiz_title": "Java QZ2", 
        "time_limit_minutes": "20", 
        "full_points": "60", 
        "author_id": "1", 
        "category_id": "3", 
        "is_visible": "1",
        "quiz_questions": []
    },
    "12": { 
        "id": "12", 
        "quiz_title": "Java QZ3", 
        "time_limit_minutes": "20", 
        "full_points": "62", 
        "author_id": "1", 
        "category_id": "3", 
        "is_visible": "1",
        "quiz_questions": []
    },
    "13": { 
        "id": "13", 
        "quiz_title": "Java QZ4", 
        "time_limit_minutes": "25", 
        "full_points": "68", 
        "author_id": "1", 
        "category_id": "3", 
        "is_visible": "0",
        "quiz_questions": []
    },
    "14": { 
        "id": "14", 
        "quiz_title": "C++ Qz1", 
        "time_limit_minutes": "25", 
        "full_points": "59", 
        "author_id": "3", 
        "category_id": "4", 
        "is_visible": "1",
        "quiz_questions": []
    },
    "15": { 
        "id": "15", 
        "quiz_title": "C++ Qz2", 
        "time_limit_minutes": "20", 
        "full_points": "57", 
        "author_id": "3", 
        "category_id": "4", 
        "is_visible": "1",
        "quiz_questions": []
    },
    "16": { 
        "id": "16", 
        "quiz_title": "C++ Qz3", 
        "time_limit_minutes": "25", 
        "full_points": "49", 
        "author_id": "3", 
        "category_id": "4", 
        "is_visible": "1",
        "quiz_questions": []
    },
    "17": { 
        "id": "17", 
        "quiz_title": "React Qz1", 
        "time_limit_minutes": "30", 
        "full_points": "82", 
        "author_id": "26", 
        "category_id": "5", 
        "is_visible": "1",
        "quiz_questions": []
    },
    "18": { 
        "id": "18", 
        "quiz_title": "React Qz2", 
        "time_limit_minutes": "25", 
        "full_points": "59", 
        "author_id": "26", 
        "category_id": "5", 
        "is_visible": "1",
        "quiz_questions": []
    },
    "19": { 
        "id": "19", 
        "quiz_title": "React Qz3", 
        "time_limit_minutes": "20", 
        "full_points": "37", 
        "author_id": "26", 
        "category_id": "5", 
        "is_visible": "1",
        "quiz_questions": []
    },
    "20": { 
        "id": "20", 
        "quiz_title": "Pyton Qz1", 
        "time_limit_minutes": "25", 
        "full_points": "58", 
        "author_id": "1", 
        "category_id": "10", 
        "is_visible": "1",
        "quiz_questions": []
    },
    "21": { 
        "id": "21", 
        "quiz_title": "Pyton Qz3", 
        "time_limit_minutes": "25", 
        "full_points": "90", 
        "author_id": "1", 
        "category_id": "10", 
        "is_visible": "1",
        "quiz_questions": []
    },
    "22": { 
        "id": "22", 
        "quiz_title": "Pyton Qz2", 
        "time_limit_minutes": "25", 
        "full_points": "47", 
        "author_id": "1", 
        "category_id": "10", 
        "is_visible": "1",
        "quiz_questions": []
    },
    "23": { 
        "id": "23", 
        "quiz_title": "Ada Qz1", 
        "time_limit_minutes": "30", 
        "full_points": "47", 
        "author_id": "3", 
        "category_id": "13", 
        "is_visible": "1",
        "quiz_questions": []
    },
    "24": { 
        "id": "24", 
        "quiz_title": "Ada Qz2", 
        "time_limit_minutes": "30", 
        "full_points": "58", 
        "author_id": "3", 
        "category_id": "13", 
        "is_visible": "1",
        "quiz_questions": []
    },
    "25": { 
        "id": "25", 
        "quiz_title": "Ada Qz3", 
        "time_limit_minutes": "20", 
        "full_points": "56", 
        "author_id": "1", 
        "category_id": "13", 
        "is_visible": "0",
        "quiz_questions": []
    },
    "28": { 
        "id": "28", 
        "quiz_title": "C# Qz1", 
        "time_limit_minutes": "25", 
        "full_points": "69", 
        "author_id": "1", 
        "category_id": "14", 
        "is_visible": "1",
        "quiz_questions": []
    },
    "29": { 
        "id": "29", 
        "quiz_title": "C# Qz2", 
        "time_limit_minutes": "29", 
        "full_points": "69", 
        "author_id": "1", 
        "category_id": "14", 
        "is_visible": "1",
        "quiz_questions": []
    },
    "30": { 
        "id": "30", 
        "quiz_title": "C# Qz3", 
        "time_limit_minutes": "40", 
        "full_points": "98", 
        "author_id": "1", 
        "category_id": "14", 
        "is_visible": "1",
        "quiz_questions": []
    },
    "31": { 
        "id": "31", 
        "quiz_title": "React Qz4", 
        "time_limit_minutes": "25", 
        "full_points": "74", 
        "author_id": "26", 
        "category_id": "5", 
        "is_visible": "1",
        "quiz_questions": []
    }
}